disquip/__init__.py
disquip/__main__.py
disquip/bot.py
disquip/discover.py
disquip/normalize.py
disquip_bot-1.1.8.dist-info/LICENSE
disquip_bot-1.1.8.dist-info/METADATA
disquip_bot-1.1.8.dist-info/WHEEL
disquip_bot-1.1.8.dist-info/entry_points.txt
disquip_bot-1.1.8.dist-info/top_level.txt
disquip_bot-1.1.8.dist-info/RECORD
