Metadata-Version: 2.1
Name: disquip-bot
Version: 1.1.8
Summary: An easy-to-use Discord soundboard bot. BYO audio files and quip away!
Home-page: https://github.com/blthayer/disquip-bot
Author: Brandon Thayer
Author-email: brandon.lewis.thayer@gmail.com
License: MIT
Platform: UNKNOWN
Classifier: Programming Language :: Python :: 3
Classifier: License :: OSI Approved :: MIT License
Classifier: Operating System :: OS Independent
Classifier: Development Status :: 4 - Beta
Classifier: Intended Audience :: End Users/Desktop
Classifier: Intended Audience :: Developers
Requires-Python: >=3.6
License-File: LICENSE
Requires-Dist: attrs (==21.4.0)
Requires-Dist: discord.py[voice] (==1.7.3)
Requires-Dist: ffmpeg-normalize (==1.23.0)
Requires-Dist: tabulate (==0.8.10)
